setup.cfg
setup.py
slda/__init__.py
slda/_topic_models.c
slda/topic_models.py
slda.egg-info/PKG-INFO
slda.egg-info/SOURCES.txt
slda.egg-info/dependency_links.txt
slda.egg-info/requires.txt
slda.egg-info/top_level.txt