Metadata-Version: 1.0
Name: slda
Version: 0.1.2
Summary: Cython implementations of Gibbs sampling for latent
Home-page: https://code.savvysherpa.com/SavvysherpaResearch/slda
Author: Berton Earnshaw, Mimi Felicilda
Author-email: bearnshaw@savvysherpa.com, lfelicilda@savvysherpa.com
License: UNKNOWN
Keywords: lda,slda,supervised,latent,Dirichlet,allocation
Platform: UNKNOWN
